autoapt/__init__.py
autoapt-1.0.dist-info/LICENSE
autoapt-1.0.dist-info/METADATA
autoapt-1.0.dist-info/WHEEL
autoapt-1.0.dist-info/top_level.txt
autoapt-1.0.dist-info/RECORD
