Metadata-Version: 2.1
Name: autoapt
Version: 1.0
Summary: Find how to install missing packages with apt-file
Home-page: https://github.com/mgajda/autoapt
Author: Michał J. Gajda
Author-email: mjgajda@migamake.com
License: BSD
Project-URL: Bug Tracker, https://github.com/mgajda/autoapt/issues
Platform: Linux
Classifier: Programming Language :: Python :: 3
Classifier: License :: OSI Approved :: BSD License
Classifier: Operating System :: POSIX :: Linux
Requires-Python: >=3.0
License-File: LICENSE
